MANIFEST.in
setup.cfg
setup.py
docs/Makefile
docs/conf.py
docs/index.txt
docs/make.bat
docs/_build/.keepthisdir
docs/_build/doctrees/environment.pickle
docs/_build/doctrees/index.doctree
docs/_build/html/.buildinfo
docs/_build/html/genindex.html
docs/_build/html/index.html
docs/_build/html/objects.inv
docs/_build/html/py-modindex.html
docs/_build/html/search.html
docs/_build/html/searchindex.js
docs/_build/html/_sources/index.txt
docs/_build/html/_static/basic.css
docs/_build/html/_static/default.css
docs/_build/html/_static/doctools.js
docs/_build/html/_static/file.png
docs/_build/html/_static/jquery.js
docs/_build/html/_static/minus.png
docs/_build/html/_static/plus.png
docs/_build/html/_static/pygments.css
docs/_build/html/_static/searchtools.js
docs/_build/html/_static/sidebar.js
docs/_build/html/_static/underscore.js
docs/_static/.dir
lib/cli/__init__.py
lib/cli/app.py
lib/cli/daemon.py
lib/cli/ext.py
lib/cli/log.py
lib/cli/profiler.py
lib/cli/test.py
lib/cli/util.py
lib/cli/_ext/__init__.py
lib/cli/_ext/argparse.py
lib/cli/_ext/scripttest.py
lib/cli/tests/__init__.py
lib/cli/tests/test_cli_app.py
lib/cli/tests/test_cli_daemon.py
lib/cli/tests/test_cli_log.py
lib/cli/tests/test_cli_profiler.py
lib/cli/tests/test_cli_util.py
lib/cli/tests/functional/__init__.py
lib/pyCLI.egg-info/PKG-INFO
lib/pyCLI.egg-info/SOURCES.txt
lib/pyCLI.egg-info/dependency_links.txt
lib/pyCLI.egg-info/entry_points.txt
lib/pyCLI.egg-info/not-zip-safe
lib/pyCLI.egg-info/top_level.txt