Metadata-Version: 1.0
Name: pyCLI
Version: 2.0.1
Summary: Simple, object-oriented approach to Python CLI apps
Home-page: http://packages.python.org/pyCLI/
Author: Will Maier
Author-email: will@m.aier.us
License: UNKNOWN
Keywords: command line application framework
Platform: UNKNOWN
Classifier: Programming Language :: Python :: 2.4
Classifier: Programming Language :: Python :: 2.5
Classifier: Programming Language :: Python :: 2.6
Classifier: Programming Language :: Python :: 2.7
Classifier: Programming Language :: Python :: 3
Classifier: Topic :: Software Development :: Libraries :: Application Frameworks
Classifier: Environment :: Console
Classifier: Development Status :: 5 - Production/Stable
